energydiagram/__init__.py
energydiagram/box_notation.py
energydiagram/energydiagram.py
energydiagram-1.0.0.dist-info/licenses/LICENSE
energydiagram-1.0.0.dist-info/METADATA
energydiagram-1.0.0.dist-info/WHEEL
energydiagram-1.0.0.dist-info/top_level.txt
energydiagram-1.0.0.dist-info/RECORD
