Metadata-Version: 2.4
Name: energydiagram
Version: 1.0.0
Summary: A tool for plotting Energy Diagrams using Matplotlib.
Author-email: Giacomo Marchioro <giacomomarchioro@outlook.com>
License: MIT
Project-URL: Homepage, https://github.com/giacomomarchioro/PyEnergyDiagrams
Keywords: energy diagram,matplotlib,chemistry,visualization
Classifier: Programming Language :: Python :: 3
Classifier: License :: OSI Approved :: MIT License
Classifier: Operating System :: OS Independent
Requires-Python: >=3.6
License-File: LICENSE
Requires-Dist: matplotlib
Dynamic: license-file
